gyp/MSVSNew.py
gyp/MSVSProject.py
gyp/MSVSSettings.py
gyp/MSVSSettings_test.py
gyp/MSVSToolFile.py
gyp/MSVSUserFile.py
gyp/MSVSUtil.py
gyp/MSVSVersion.py
gyp/__init__.py
gyp/common.py
gyp/common_test.py
gyp/easy_xml.py
gyp/easy_xml_test.py
gyp/flock_tool.py
gyp/input.py
gyp/input_test.py
gyp/mac_tool.py
gyp/msvs_emulation.py
gyp/ninja_syntax.py
gyp/simple_copy.py
gyp/win_tool.py
gyp/xcode_emulation.py
gyp/xcode_emulation_test.py
gyp/xcode_ninja.py
gyp/xcodeproj_file.py
gyp/xml_fix.py
gyp/generator/__init__.py
gyp/generator/analyzer.py
gyp/generator/android.py
gyp/generator/cmake.py
gyp/generator/compile_commands_json.py
gyp/generator/dump_dependency_json.py
gyp/generator/eclipse.py
gyp/generator/gypd.py
gyp/generator/gypsh.py
gyp/generator/make.py
gyp/generator/msvs.py
gyp/generator/msvs_test.py
gyp/generator/ninja.py
gyp/generator/ninja_test.py
gyp/generator/xcode.py
gyp/generator/xcode_test.py
gyp_next-0.21.0.dist-info/licenses/AUTHORS
gyp_next-0.21.0.dist-info/licenses/LICENSE
gyp_next-0.21.0.dist-info/METADATA
gyp_next-0.21.0.dist-info/WHEEL
gyp_next-0.21.0.dist-info/entry_points.txt
gyp_next-0.21.0.dist-info/top_level.txt
gyp_next-0.21.0.dist-info/RECORD
