Metadata-Version: 2.4
Name: gyp-next
Version: 0.21.0
Summary: A fork of the GYP build system for use in the Node.js projects
Author-email: "Node.js contributors" <ryzokuken@disroot.org>
License: Copyright (c) 2020 Node.js contributors. All rights reserved.
Project-URL: Homepage, https://github.com/nodejs/gyp-next
Classifier: Development Status :: 3 - Alpha
Classifier: Environment :: Console
Classifier: Intended Audience :: Developers
Classifier: License :: OSI Approved :: BSD License
Classifier: Natural Language :: English
Classifier: Programming Language :: Python
Classifier: Programming Language :: Python :: 3
Classifier: Programming Language :: Python :: 3.8
Classifier: Programming Language :: Python :: 3.9
Classifier: Programming Language :: Python :: 3.10
Classifier: Programming Language :: Python :: 3.11
Requires-Python: >=3.8
License-File: LICENSE
License-File: AUTHORS
Requires-Dist: packaging>=24.0
Requires-Dist: setuptools>=69.5.1
Provides-Extra: dev
Requires-Dist: pytest; extra == "dev"
Requires-Dist: ruff; extra == "dev"
Dynamic: license-file
